setup.cfg
setup.py
opp/__init__.py
opp/config.py
opp/core.py
opp/facade.py
opp/utils.py
opp.egg-info/PKG-INFO
opp.egg-info/SOURCES.txt
opp.egg-info/dependency_links.txt
opp.egg-info/requires.txt
opp.egg-info/top_level.txt