Metadata-Version: 1.1
Name: opp
Version: 1.2.0
Summary: Python wrapper for OPP
Home-page: https://github.com/OpenPaymentPlatform/python
Author: PAY.ON
Author-email: opp@payon.com
License: MIT
Download-URL: https://github.com/OpenPaymentPlatform/python/tarball/1.2.0
Platform: UNKNOWN
Classifier: Development Status :: 5 - Production/Stable
Classifier: Environment :: Web Environment
Classifier: Intended Audience :: Developers
Classifier: Operating System :: OS Independent
Classifier: Programming Language :: Python
Classifier: Programming Language :: Python :: 3
Classifier: License :: OSI Approved :: MIT License
Classifier: Topic :: Internet :: WWW/HTTP
Classifier: Topic :: Software Development :: Libraries :: Python Modules
